Metadata-Version: 2.1
Name: kathurima
Version: 1.0.0
Summary: A sample project on testing python packaging
Home-page: https://github.com/KathurimaKimathi/pythonproject
Author: KathurimaKimathi
Author-email: kathurimakimathi@gmail.com
License: UNKNOWN
Keywords: sample setuptools development
Platform: UNKNOWN
Classifier: Intended Audience :: Developers
Classifier: Topic :: Software Development :: Build Tools
Classifier: License :: OSI Approved :: MIT License
Classifier: Programming Language :: Python :: 2
Classifier: Programming Language :: Python :: 2.7
Classifier: Programming Language :: Python :: 3
Classifier: Programming Language :: Python :: 3.4
Classifier: Programming Language :: Python :: 3.5
Classifier: Programming Language :: Python :: 3.6
Classifier: Programming Language :: Python :: 3.7
Requires-Python: >=2.7, !=3.0.*, !=3.1.*, !=3.2.*, !=3.3.*, <4
